{
  "generation": [
    {
      "templateId": "ui5template.basicSAPUI5ApplicationProject",
      "templateVersion": "1.4.0",
      "dateTimeStamp": "Sat, 26 Sep 2015 17:35:56 GMT"
    }
  ],
  "translation": {
    "translationDomain": "",
    "supportedLanguages": "en,fr,de",
    "defaultLanguage": "en",
    "defaultI18NPropertyFile": "i18n.properties",
    "resourceModelName": "i18n"
  },
  "hcpdeploy": {
    "account": "d062712trial",
    "name": "chucknorrisjokes",
    "lastVersionWeTriedToDeploy": "1.0.6"
  }
}