{  
   "d":{  
      "results":[  
         {  
            "__metadata":{  
               "type":"usernametrial.dev.swapi.services.PeopleType",
               "uri":"https://s8hanaxs.hanatrial.ondemand.com:443/usernametrial/dev/swapi/services/api.xsodata/People(1)"
            },
            "ID":1,
            "NAME":"Luke Skywalker",
            "HEIGHT":172,
            "MASS":77,
            "HAIR_COLOR":"blond",
            "SKIN_COLOR":"fair",
            "EYE_COLOR":"blue",
            "BIRTH_YEAR":"19BBY",
            "GENDER":"male",
            "SPECIES_ID":1,
            "Starships":{  
               "__deferred":{  
                  "uri":"https://s8hanaxs.hanatrial.ondemand.com:443/usernametrial/dev/swapi/services/api.xsodata/People(1)/Starships"
               }
            },
            "Species":{  
               "__deferred":{  
                  "uri":"https://s8hanaxs.hanatrial.ondemand.com:443/usernametrial/dev/swapi/services/api.xsodata/People(1)/Species"
               }
            }
         },
         {  
            "__metadata":{  
               "type":"usernametrial.dev.swapi.services.PeopleType",
               "uri":"https://s8hanaxs.hanatrial.ondemand.com:443/usernametrial/dev/swapi/services/api.xsodata/People(2)"
            },
            "ID":2,
            "NAME":"C-3PO",
            "HEIGHT":167,
            "MASS":75,
            "HAIR_COLOR":"n/a",
            "SKIN_COLOR":"gold",
            "EYE_COLOR":"yellow",
            "BIRTH_YEAR":"112BBY",
            "GENDER":"n/a",
            "SPECIES_ID":2,
            "Starships":{  
               "__deferred":{  
                  "uri":"https://s8hanaxs.hanatrial.ondemand.com:443/usernametrial/dev/swapi/services/api.xsodata/People(2)/Starships"
               }
            },
            "Species":{  
               "__deferred":{  
                  "uri":"https://s8hanaxs.hanatrial.ondemand.com:443/usernametrial/dev/swapi/services/api.xsodata/People(2)/Species"
               }
            }
         },
         {  
            "__metadata":{  
               "type":"usernametrial.dev.swapi.services.PeopleType",
               "uri":"https://s8hanaxs.hanatrial.ondemand.com:443/usernametrial/dev/swapi/services/api.xsodata/People(3)"
            },
            "ID":3,
            "NAME":"R2-D2",
            "HEIGHT":96,
            "MASS":32,
            "HAIR_COLOR":"n/a",
            "SKIN_COLOR":"white, blue",
            "EYE_COLOR":"red",
            "BIRTH_YEAR":"33BBY",
            "GENDER":"n/a",
            "SPECIES_ID":2,
            "Starships":{  
               "__deferred":{  
                  "uri":"https://s8hanaxs.hanatrial.ondemand.com:443/usernametrial/dev/swapi/services/api.xsodata/People(3)/Starships"
               }
            },
            "Species":{  
               "__deferred":{  
                  "uri":"https://s8hanaxs.hanatrial.ondemand.com:443/usernametrial/dev/swapi/services/api.xsodata/People(3)/Species"
               }
            }
         },
         {  
            "__metadata":{  
               "type":"usernametrial.dev.swapi.services.PeopleType",
               "uri":"https://s8hanaxs.hanatrial.ondemand.com:443/usernametrial/dev/swapi/services/api.xsodata/People(4)"
            },
            "ID":4,
            "NAME":"Darth Vader",
            "HEIGHT":202,
            "MASS":136,
            "HAIR_COLOR":"none",
            "SKIN_COLOR":"white",
            "EYE_COLOR":"yellow",
            "BIRTH_YEAR":"41.9BBY",
            "GENDER":"male",
            "SPECIES_ID":1,
            "Starships":{  
               "__deferred":{  
                  "uri":"https://s8hanaxs.hanatrial.ondemand.com:443/usernametrial/dev/swapi/services/api.xsodata/People(4)/Starships"
               }
            },
            "Species":{  
               "__deferred":{  
                  "uri":"https://s8hanaxs.hanatrial.ondemand.com:443/usernametrial/dev/swapi/services/api.xsodata/People(4)/Species"
               }
            }
         },
         {  
            "__metadata":{  
               "type":"usernametrial.dev.swapi.services.PeopleType",
               "uri":"https://s8hanaxs.hanatrial.ondemand.com:443/usernametrial/dev/swapi/services/api.xsodata/People(5)"
            },
            "ID":5,
            "NAME":"Leia Organa",
            "HEIGHT":150,
            "MASS":49,
            "HAIR_COLOR":"brown",
            "SKIN_COLOR":"light",
            "EYE_COLOR":"brown",
            "BIRTH_YEAR":"19BBY",
            "GENDER":"female",
            "SPECIES_ID":1,
            "Starships":{  
               "__deferred":{  
                  "uri":"https://s8hanaxs.hanatrial.ondemand.com:443/usernametrial/dev/swapi/services/api.xsodata/People(5)/Starships"
               }
            },
            "Species":{  
               "__deferred":{  
                  "uri":"https://s8hanaxs.hanatrial.ondemand.com:443/usernametrial/dev/swapi/services/api.xsodata/People(5)/Species"
               }
            }
         },
         {  
            "__metadata":{  
               "type":"usernametrial.dev.swapi.services.PeopleType",
               "uri":"https://s8hanaxs.hanatrial.ondemand.com:443/usernametrial/dev/swapi/services/api.xsodata/People(6)"
            },
            "ID":6,
            "NAME":"Owen Lars",
            "HEIGHT":178,
            "MASS":120,
            "HAIR_COLOR":"brown, grey",
            "SKIN_COLOR":"light",
            "EYE_COLOR":"blue",
            "BIRTH_YEAR":"52BBY",
            "GENDER":"male",
            "SPECIES_ID":1,
            "Starships":{  
               "__deferred":{  
                  "uri":"https://s8hanaxs.hanatrial.ondemand.com:443/usernametrial/dev/swapi/services/api.xsodata/People(6)/Starships"
               }
            },
            "Species":{  
               "__deferred":{  
                  "uri":"https://s8hanaxs.hanatrial.ondemand.com:443/usernametrial/dev/swapi/services/api.xsodata/People(6)/Species"
               }
            }
         },
         {  
            "__metadata":{  
               "type":"usernametrial.dev.swapi.services.PeopleType",
               "uri":"https://s8hanaxs.hanatrial.ondemand.com:443/usernametrial/dev/swapi/services/api.xsodata/People(7)"
            },
            "ID":7,
            "NAME":"Beru Whitesun lars",
            "HEIGHT":165,
            "MASS":75,
            "HAIR_COLOR":"brown",
            "SKIN_COLOR":"light",
            "EYE_COLOR":"blue",
            "BIRTH_YEAR":"47BBY",
            "GENDER":"female",
            "SPECIES_ID":1,
            "Starships":{  
               "__deferred":{  
                  "uri":"https://s8hanaxs.hanatrial.ondemand.com:443/usernametrial/dev/swapi/services/api.xsodata/People(7)/Starships"
               }
            },
            "Species":{  
               "__deferred":{  
                  "uri":"https://s8hanaxs.hanatrial.ondemand.com:443/usernametrial/dev/swapi/services/api.xsodata/People(7)/Species"
               }
            }
         },
         {  
            "__metadata":{  
               "type":"usernametrial.dev.swapi.services.PeopleType",
               "uri":"https://s8hanaxs.hanatrial.ondemand.com:443/usernametrial/dev/swapi/services/api.xsodata/People(8)"
            },
            "ID":8,
            "NAME":"R5-D4",
            "HEIGHT":97,
            "MASS":32,
            "HAIR_COLOR":"n/a",
            "SKIN_COLOR":"white, red",
            "EYE_COLOR":"red",
            "BIRTH_YEAR":"unknown",
            "GENDER":"n/a",
            "SPECIES_ID":2,
            "Starships":{  
               "__deferred":{  
                  "uri":"https://s8hanaxs.hanatrial.ondemand.com:443/usernametrial/dev/swapi/services/api.xsodata/People(8)/Starships"
               }
            },
            "Species":{  
               "__deferred":{  
                  "uri":"https://s8hanaxs.hanatrial.ondemand.com:443/usernametrial/dev/swapi/services/api.xsodata/People(8)/Species"
               }
            }
         },
         {  
            "__metadata":{  
               "type":"usernametrial.dev.swapi.services.PeopleType",
               "uri":"https://s8hanaxs.hanatrial.ondemand.com:443/usernametrial/dev/swapi/services/api.xsodata/People(9)"
            },
            "ID":9,
            "NAME":"Biggs Darklighter",
            "HEIGHT":183,
            "MASS":84,
            "HAIR_COLOR":"black",
            "SKIN_COLOR":"light",
            "EYE_COLOR":"brown",
            "BIRTH_YEAR":"24BBY",
            "GENDER":"male",
            "SPECIES_ID":1,
            "Starships":{  
               "__deferred":{  
                  "uri":"https://s8hanaxs.hanatrial.ondemand.com:443/usernametrial/dev/swapi/services/api.xsodata/People(9)/Starships"
               }
            },
            "Species":{  
               "__deferred":{  
                  "uri":"https://s8hanaxs.hanatrial.ondemand.com:443/usernametrial/dev/swapi/services/api.xsodata/People(9)/Species"
               }
            }
         },
         {  
            "__metadata":{  
               "type":"usernametrial.dev.swapi.services.PeopleType",
               "uri":"https://s8hanaxs.hanatrial.ondemand.com:443/usernametrial/dev/swapi/services/api.xsodata/People(10)"
            },
            "ID":10,
            "NAME":"Obi-Wan Kenobi",
            "HEIGHT":182,
            "MASS":77,
            "HAIR_COLOR":"auburn, white",
            "SKIN_COLOR":"fair",
            "EYE_COLOR":"blue-gray",
            "BIRTH_YEAR":"57BBY",
            "GENDER":"male",
            "SPECIES_ID":1,
            "Starships":{  
               "__deferred":{  
                  "uri":"https://s8hanaxs.hanatrial.ondemand.com:443/usernametrial/dev/swapi/services/api.xsodata/People(10)/Starships"
               }
            },
            "Species":{  
               "__deferred":{  
                  "uri":"https://s8hanaxs.hanatrial.ondemand.com:443/usernametrial/dev/swapi/services/api.xsodata/People(10)/Species"
               }
            }
         },
         {  
            "__metadata":{  
               "type":"usernametrial.dev.swapi.services.PeopleType",
               "uri":"https://s8hanaxs.hanatrial.ondemand.com:443/usernametrial/dev/swapi/services/api.xsodata/People(11)"
            },
            "ID":11,
            "NAME":"Anakin Skywalker",
            "HEIGHT":188,
            "MASS":84,
            "HAIR_COLOR":"blond",
            "SKIN_COLOR":"fair",
            "EYE_COLOR":"blue",
            "BIRTH_YEAR":"41.9BBY",
            "GENDER":"male",
            "SPECIES_ID":1,
            "Starships":{  
               "__deferred":{  
                  "uri":"https://s8hanaxs.hanatrial.ondemand.com:443/usernametrial/dev/swapi/services/api.xsodata/People(11)/Starships"
               }
            },
            "Species":{  
               "__deferred":{  
                  "uri":"https://s8hanaxs.hanatrial.ondemand.com:443/usernametrial/dev/swapi/services/api.xsodata/People(11)/Species"
               }
            }
         },
         {  
            "__metadata":{  
               "type":"usernametrial.dev.swapi.services.PeopleType",
               "uri":"https://s8hanaxs.hanatrial.ondemand.com:443/usernametrial/dev/swapi/services/api.xsodata/People(12)"
            },
            "ID":12,
            "NAME":"Wilhuff Tarkin",
            "HEIGHT":180,
            "MASS":0,
            "HAIR_COLOR":"auburn, grey",
            "SKIN_COLOR":"fair",
            "EYE_COLOR":"blue",
            "BIRTH_YEAR":"64BBY",
            "GENDER":"male",
            "SPECIES_ID":1,
            "Starships":{  
               "__deferred":{  
                  "uri":"https://s8hanaxs.hanatrial.ondemand.com:443/usernametrial/dev/swapi/services/api.xsodata/People(12)/Starships"
               }
            },
            "Species":{  
               "__deferred":{  
                  "uri":"https://s8hanaxs.hanatrial.ondemand.com:443/usernametrial/dev/swapi/services/api.xsodata/People(12)/Species"
               }
            }
         },
         {  
            "__metadata":{  
               "type":"usernametrial.dev.swapi.services.PeopleType",
               "uri":"https://s8hanaxs.hanatrial.ondemand.com:443/usernametrial/dev/swapi/services/api.xsodata/People(13)"
            },
            "ID":13,
            "NAME":"Chewbacca",
            "HEIGHT":228,
            "MASS":112,
            "HAIR_COLOR":"brown",
            "SKIN_COLOR":"unknown",
            "EYE_COLOR":"blue",
            "BIRTH_YEAR":"200BBY",
            "GENDER":"male",
            "SPECIES_ID":3,
            "Starships":{  
               "__deferred":{  
                  "uri":"https://s8hanaxs.hanatrial.ondemand.com:443/usernametrial/dev/swapi/services/api.xsodata/People(13)/Starships"
               }
            },
            "Species":{  
               "__deferred":{  
                  "uri":"https://s8hanaxs.hanatrial.ondemand.com:443/usernametrial/dev/swapi/services/api.xsodata/People(13)/Species"
               }
            }
         },
         {  
            "__metadata":{  
               "type":"usernametrial.dev.swapi.services.PeopleType",
               "uri":"https://s8hanaxs.hanatrial.ondemand.com:443/usernametrial/dev/swapi/services/api.xsodata/People(14)"
            },
            "ID":14,
            "NAME":"Han Solo",
            "HEIGHT":180,
            "MASS":80,
            "HAIR_COLOR":"brown",
            "SKIN_COLOR":"fair",
            "EYE_COLOR":"brown",
            "BIRTH_YEAR":"29BBY",
            "GENDER":"male",
            "SPECIES_ID":1,
            "Starships":{  
               "__deferred":{  
                  "uri":"https://s8hanaxs.hanatrial.ondemand.com:443/usernametrial/dev/swapi/services/api.xsodata/People(14)/Starships"
               }
            },
            "Species":{  
               "__deferred":{  
                  "uri":"https://s8hanaxs.hanatrial.ondemand.com:443/usernametrial/dev/swapi/services/api.xsodata/People(14)/Species"
               }
            }
         },
         {  
            "__metadata":{  
               "type":"usernametrial.dev.swapi.services.PeopleType",
               "uri":"https://s8hanaxs.hanatrial.ondemand.com:443/usernametrial/dev/swapi/services/api.xsodata/People(15)"
            },
            "ID":15,
            "NAME":"Greedo",
            "HEIGHT":173,
            "MASS":74,
            "HAIR_COLOR":"n/a",
            "SKIN_COLOR":"green",
            "EYE_COLOR":"black",
            "BIRTH_YEAR":"44BBY",
            "GENDER":"male",
            "SPECIES_ID":4,
            "Starships":{  
               "__deferred":{  
                  "uri":"https://s8hanaxs.hanatrial.ondemand.com:443/usernametrial/dev/swapi/services/api.xsodata/People(15)/Starships"
               }
            },
            "Species":{  
               "__deferred":{  
                  "uri":"https://s8hanaxs.hanatrial.ondemand.com:443/usernametrial/dev/swapi/services/api.xsodata/People(15)/Species"
               }
            }
         },
         {  
            "__metadata":{  
               "type":"usernametrial.dev.swapi.services.PeopleType",
               "uri":"https://s8hanaxs.hanatrial.ondemand.com:443/usernametrial/dev/swapi/services/api.xsodata/People(16)"
            },
            "ID":16,
            "NAME":"Jabba Desilijic Tiure",
            "HEIGHT":175,
            "MASS":1358,
            "HAIR_COLOR":"n/a",
            "SKIN_COLOR":"green-tan, brown",
            "EYE_COLOR":"orange",
            "BIRTH_YEAR":"600BBY",
            "GENDER":"hermaphrodite",
            "SPECIES_ID":5,
            "Starships":{  
               "__deferred":{  
                  "uri":"https://s8hanaxs.hanatrial.ondemand.com:443/usernametrial/dev/swapi/services/api.xsodata/People(16)/Starships"
               }
            },
            "Species":{  
               "__deferred":{  
                  "uri":"https://s8hanaxs.hanatrial.ondemand.com:443/usernametrial/dev/swapi/services/api.xsodata/People(16)/Species"
               }
            }
         },
         {  
            "__metadata":{  
               "type":"usernametrial.dev.swapi.services.PeopleType",
               "uri":"https://s8hanaxs.hanatrial.ondemand.com:443/usernametrial/dev/swapi/services/api.xsodata/People(17)"
            },
            "ID":17,
            "NAME":"Wedge Antilles",
            "HEIGHT":170,
            "MASS":77,
            "HAIR_COLOR":"brown",
            "SKIN_COLOR":"fair",
            "EYE_COLOR":"hazel",
            "BIRTH_YEAR":"21BBY",
            "GENDER":"male",
            "SPECIES_ID":1,
            "Starships":{  
               "__deferred":{  
                  "uri":"https://s8hanaxs.hanatrial.ondemand.com:443/usernametrial/dev/swapi/services/api.xsodata/People(17)/Starships"
               }
            },
            "Species":{  
               "__deferred":{  
                  "uri":"https://s8hanaxs.hanatrial.ondemand.com:443/usernametrial/dev/swapi/services/api.xsodata/People(17)/Species"
               }
            }
         },
         {  
            "__metadata":{  
               "type":"usernametrial.dev.swapi.services.PeopleType",
               "uri":"https://s8hanaxs.hanatrial.ondemand.com:443/usernametrial/dev/swapi/services/api.xsodata/People(18)"
            },
            "ID":18,
            "NAME":"Jek Tono Porkins",
            "HEIGHT":180,
            "MASS":110,
            "HAIR_COLOR":"brown",
            "SKIN_COLOR":"fair",
            "EYE_COLOR":"blue",
            "BIRTH_YEAR":"unknown",
            "GENDER":"male",
            "SPECIES_ID":1,
            "Starships":{  
               "__deferred":{  
                  "uri":"https://s8hanaxs.hanatrial.ondemand.com:443/usernametrial/dev/swapi/services/api.xsodata/People(18)/Starships"
               }
            },
            "Species":{  
               "__deferred":{  
                  "uri":"https://s8hanaxs.hanatrial.ondemand.com:443/usernametrial/dev/swapi/services/api.xsodata/People(18)/Species"
               }
            }
         },
         {  
            "__metadata":{  
               "type":"usernametrial.dev.swapi.services.PeopleType",
               "uri":"https://s8hanaxs.hanatrial.ondemand.com:443/usernametrial/dev/swapi/services/api.xsodata/People(19)"
            },
            "ID":19,
            "NAME":"Yoda",
            "HEIGHT":66,
            "MASS":17,
            "HAIR_COLOR":"white",
            "SKIN_COLOR":"green",
            "EYE_COLOR":"brown",
            "BIRTH_YEAR":"896BBY",
            "GENDER":"male",
            "SPECIES_ID":6,
            "Starships":{  
               "__deferred":{  
                  "uri":"https://s8hanaxs.hanatrial.ondemand.com:443/usernametrial/dev/swapi/services/api.xsodata/People(19)/Starships"
               }
            },
            "Species":{  
               "__deferred":{  
                  "uri":"https://s8hanaxs.hanatrial.ondemand.com:443/usernametrial/dev/swapi/services/api.xsodata/People(19)/Species"
               }
            }
         },
         {  
            "__metadata":{  
               "type":"usernametrial.dev.swapi.services.PeopleType",
               "uri":"https://s8hanaxs.hanatrial.ondemand.com:443/usernametrial/dev/swapi/services/api.xsodata/People(20)"
            },
            "ID":20,
            "NAME":"Palpatine",
            "HEIGHT":170,
            "MASS":75,
            "HAIR_COLOR":"grey",
            "SKIN_COLOR":"pale",
            "EYE_COLOR":"yellow",
            "BIRTH_YEAR":"82BBY",
            "GENDER":"male",
            "SPECIES_ID":1,
            "Starships":{  
               "__deferred":{  
                  "uri":"https://s8hanaxs.hanatrial.ondemand.com:443/usernametrial/dev/swapi/services/api.xsodata/People(20)/Starships"
               }
            },
            "Species":{  
               "__deferred":{  
                  "uri":"https://s8hanaxs.hanatrial.ondemand.com:443/usernametrial/dev/swapi/services/api.xsodata/People(20)/Species"
               }
            }
         },
         {  
            "__metadata":{  
               "type":"usernametrial.dev.swapi.services.PeopleType",
               "uri":"https://s8hanaxs.hanatrial.ondemand.com:443/usernametrial/dev/swapi/services/api.xsodata/People(21)"
            },
            "ID":21,
            "NAME":"Boba Fett",
            "HEIGHT":183,
            "MASS":78,
            "HAIR_COLOR":"black",
            "SKIN_COLOR":"fair",
            "EYE_COLOR":"brown",
            "BIRTH_YEAR":"31.5BBY",
            "GENDER":"male",
            "SPECIES_ID":1,
            "Starships":{  
               "__deferred":{  
                  "uri":"https://s8hanaxs.hanatrial.ondemand.com:443/usernametrial/dev/swapi/services/api.xsodata/People(21)/Starships"
               }
            },
            "Species":{  
               "__deferred":{  
                  "uri":"https://s8hanaxs.hanatrial.ondemand.com:443/usernametrial/dev/swapi/services/api.xsodata/People(21)/Species"
               }
            }
         },
         {  
            "__metadata":{  
               "type":"usernametrial.dev.swapi.services.PeopleType",
               "uri":"https://s8hanaxs.hanatrial.ondemand.com:443/usernametrial/dev/swapi/services/api.xsodata/People(22)"
            },
            "ID":22,
            "NAME":"IG-88",
            "HEIGHT":200,
            "MASS":140,
            "HAIR_COLOR":"none",
            "SKIN_COLOR":"metal",
            "EYE_COLOR":"red",
            "BIRTH_YEAR":"15BBY",
            "GENDER":"none",
            "SPECIES_ID":2,
            "Starships":{  
               "__deferred":{  
                  "uri":"https://s8hanaxs.hanatrial.ondemand.com:443/usernametrial/dev/swapi/services/api.xsodata/People(22)/Starships"
               }
            },
            "Species":{  
               "__deferred":{  
                  "uri":"https://s8hanaxs.hanatrial.ondemand.com:443/usernametrial/dev/swapi/services/api.xsodata/People(22)/Species"
               }
            }
         },
         {  
            "__metadata":{  
               "type":"usernametrial.dev.swapi.services.PeopleType",
               "uri":"https://s8hanaxs.hanatrial.ondemand.com:443/usernametrial/dev/swapi/services/api.xsodata/People(23)"
            },
            "ID":23,
            "NAME":"Bossk",
            "HEIGHT":190,
            "MASS":113,
            "HAIR_COLOR":"none",
            "SKIN_COLOR":"green",
            "EYE_COLOR":"red",
            "BIRTH_YEAR":"53BBY",
            "GENDER":"male",
            "SPECIES_ID":7,
            "Starships":{  
               "__deferred":{  
                  "uri":"https://s8hanaxs.hanatrial.ondemand.com:443/usernametrial/dev/swapi/services/api.xsodata/People(23)/Starships"
               }
            },
            "Species":{  
               "__deferred":{  
                  "uri":"https://s8hanaxs.hanatrial.ondemand.com:443/usernametrial/dev/swapi/services/api.xsodata/People(23)/Species"
               }
            }
         },
         {  
            "__metadata":{  
               "type":"usernametrial.dev.swapi.services.PeopleType",
               "uri":"https://s8hanaxs.hanatrial.ondemand.com:443/usernametrial/dev/swapi/services/api.xsodata/People(24)"
            },
            "ID":24,
            "NAME":"Lando Calrissian",
            "HEIGHT":177,
            "MASS":79,
            "HAIR_COLOR":"black",
            "SKIN_COLOR":"dark",
            "EYE_COLOR":"brown",
            "BIRTH_YEAR":"31BBY",
            "GENDER":"male",
            "SPECIES_ID":1,
            "Starships":{  
               "__deferred":{  
                  "uri":"https://s8hanaxs.hanatrial.ondemand.com:443/usernametrial/dev/swapi/services/api.xsodata/People(24)/Starships"
               }
            },
            "Species":{  
               "__deferred":{  
                  "uri":"https://s8hanaxs.hanatrial.ondemand.com:443/usernametrial/dev/swapi/services/api.xsodata/People(24)/Species"
               }
            }
         },
         {  
            "__metadata":{  
               "type":"usernametrial.dev.swapi.services.PeopleType",
               "uri":"https://s8hanaxs.hanatrial.ondemand.com:443/usernametrial/dev/swapi/services/api.xsodata/People(25)"
            },
            "ID":25,
            "NAME":"Lobot",
            "HEIGHT":175,
            "MASS":79,
            "HAIR_COLOR":"none",
            "SKIN_COLOR":"light",
            "EYE_COLOR":"blue",
            "BIRTH_YEAR":"37BBY",
            "GENDER":"male",
            "SPECIES_ID":1,
            "Starships":{  
               "__deferred":{  
                  "uri":"https://s8hanaxs.hanatrial.ondemand.com:443/usernametrial/dev/swapi/services/api.xsodata/People(25)/Starships"
               }
            },
            "Species":{  
               "__deferred":{  
                  "uri":"https://s8hanaxs.hanatrial.ondemand.com:443/usernametrial/dev/swapi/services/api.xsodata/People(25)/Species"
               }
            }
         },
         {  
            "__metadata":{  
               "type":"usernametrial.dev.swapi.services.PeopleType",
               "uri":"https://s8hanaxs.hanatrial.ondemand.com:443/usernametrial/dev/swapi/services/api.xsodata/People(26)"
            },
            "ID":26,
            "NAME":"Ackbar",
            "HEIGHT":180,
            "MASS":83,
            "HAIR_COLOR":"none",
            "SKIN_COLOR":"brown mottle",
            "EYE_COLOR":"orange",
            "BIRTH_YEAR":"41BBY",
            "GENDER":"male",
            "SPECIES_ID":8,
            "Starships":{  
               "__deferred":{  
                  "uri":"https://s8hanaxs.hanatrial.ondemand.com:443/usernametrial/dev/swapi/services/api.xsodata/People(26)/Starships"
               }
            },
            "Species":{  
               "__deferred":{  
                  "uri":"https://s8hanaxs.hanatrial.ondemand.com:443/usernametrial/dev/swapi/services/api.xsodata/People(26)/Species"
               }
            }
         },
         {  
            "__metadata":{  
               "type":"usernametrial.dev.swapi.services.PeopleType",
               "uri":"https://s8hanaxs.hanatrial.ondemand.com:443/usernametrial/dev/swapi/services/api.xsodata/People(27)"
            },
            "ID":27,
            "NAME":"Mon Mothma",
            "HEIGHT":150,
            "MASS":0,
            "HAIR_COLOR":"auburn",
            "SKIN_COLOR":"fair",
            "EYE_COLOR":"blue",
            "BIRTH_YEAR":"48BBY",
            "GENDER":"female",
            "SPECIES_ID":1,
            "Starships":{  
               "__deferred":{  
                  "uri":"https://s8hanaxs.hanatrial.ondemand.com:443/usernametrial/dev/swapi/services/api.xsodata/People(27)/Starships"
               }
            },
            "Species":{  
               "__deferred":{  
                  "uri":"https://s8hanaxs.hanatrial.ondemand.com:443/usernametrial/dev/swapi/services/api.xsodata/People(27)/Species"
               }
            }
         },
         {  
            "__metadata":{  
               "type":"usernametrial.dev.swapi.services.PeopleType",
               "uri":"https://s8hanaxs.hanatrial.ondemand.com:443/usernametrial/dev/swapi/services/api.xsodata/People(28)"
            },
            "ID":28,
            "NAME":"Arvel Crynyd",
            "HEIGHT":0,
            "MASS":0,
            "HAIR_COLOR":"brown",
            "SKIN_COLOR":"fair",
            "EYE_COLOR":"brown",
            "BIRTH_YEAR":"unknown",
            "GENDER":"male",
            "SPECIES_ID":1,
            "Starships":{  
               "__deferred":{  
                  "uri":"https://s8hanaxs.hanatrial.ondemand.com:443/usernametrial/dev/swapi/services/api.xsodata/People(28)/Starships"
               }
            },
            "Species":{  
               "__deferred":{  
                  "uri":"https://s8hanaxs.hanatrial.ondemand.com:443/usernametrial/dev/swapi/services/api.xsodata/People(28)/Species"
               }
            }
         },
         {  
            "__metadata":{  
               "type":"usernametrial.dev.swapi.services.PeopleType",
               "uri":"https://s8hanaxs.hanatrial.ondemand.com:443/usernametrial/dev/swapi/services/api.xsodata/People(29)"
            },
            "ID":29,
            "NAME":"Wicket Systri Warrick",
            "HEIGHT":88,
            "MASS":20,
            "HAIR_COLOR":"brown",
            "SKIN_COLOR":"brown",
            "EYE_COLOR":"brown",
            "BIRTH_YEAR":"8BBY",
            "GENDER":"male",
            "SPECIES_ID":9,
            "Starships":{  
               "__deferred":{  
                  "uri":"https://s8hanaxs.hanatrial.ondemand.com:443/usernametrial/dev/swapi/services/api.xsodata/People(29)/Starships"
               }
            },
            "Species":{  
               "__deferred":{  
                  "uri":"https://s8hanaxs.hanatrial.ondemand.com:443/usernametrial/dev/swapi/services/api.xsodata/People(29)/Species"
               }
            }
         },
         {  
            "__metadata":{  
               "type":"usernametrial.dev.swapi.services.PeopleType",
               "uri":"https://s8hanaxs.hanatrial.ondemand.com:443/usernametrial/dev/swapi/services/api.xsodata/People(30)"
            },
            "ID":30,
            "NAME":"Nien Nunb",
            "HEIGHT":160,
            "MASS":68,
            "HAIR_COLOR":"none",
            "SKIN_COLOR":"grey",
            "EYE_COLOR":"black",
            "BIRTH_YEAR":"unknown",
            "GENDER":"male",
            "SPECIES_ID":10,
            "Starships":{  
               "__deferred":{  
                  "uri":"https://s8hanaxs.hanatrial.ondemand.com:443/usernametrial/dev/swapi/services/api.xsodata/People(30)/Starships"
               }
            },
            "Species":{  
               "__deferred":{  
                  "uri":"https://s8hanaxs.hanatrial.ondemand.com:443/usernametrial/dev/swapi/services/api.xsodata/People(30)/Species"
               }
            }
         },
         {  
            "__metadata":{  
               "type":"usernametrial.dev.swapi.services.PeopleType",
               "uri":"https://s8hanaxs.hanatrial.ondemand.com:443/usernametrial/dev/swapi/services/api.xsodata/People(88)"
            },
            "ID":88,
            "NAME":"BB8",
            "HEIGHT":75,
            "MASS":25,
            "HAIR_COLOR":"none",
            "SKIN_COLOR":"white orange",
            "EYE_COLOR":"black",
            "BIRTH_YEAR":"unknown",
            "GENDER":"unknown",
            "SPECIES_ID":2,
            "Starships":{  
               "__deferred":{  
                  "uri":"https://s8hanaxs.hanatrial.ondemand.com:443/usernametrial/dev/swapi/services/api.xsodata/People(88)/Starships"
               }
            },
            "Species":{  
               "__deferred":{  
                  "uri":"https://s8hanaxs.hanatrial.ondemand.com:443/usernametrial/dev/swapi/services/api.xsodata/People(88)/Species"
               }
            }
         }
      ]
   }
}